<?xml version="1.0" encoding="UTF-8"?>
<SystemProperties><SystemName>12-80312</SystemName><SerialNo>12-80312</SerialNo><UsedMedia><Media path="T:\MEDIAPOOL\ROBOTWARE_5.14.1032" name="RobotWare" version="5.14.1032.01"></Media></UsedMedia><ControlModule><Key>xCiiiii.E.CK8iikiiiiiJ</Key><SignatureNr>161</SignatureNr><Category descr="OS">RobotWare OS and English</Category><Category descr="Options">748-1 DeviceNet Lean</Category><Option descr="RW Control module key"></Option><Option descr="RobotWare OS and English"></Option><Option descr="748-1 DeviceNet Lean"></Option></ControlModule><DriveModule><Name>DriveModule1</Name><Key>3X9JjZjMIqHk</Key><SignatureNr>160</SignatureNr><Category descr="Manipulators">ABB standard manipulator</Category><Category descr="Manipulators">Drive System 09 120/140/1400/1600 Compact</Category><Category descr="Manipulators">IRB 120</Category><Category descr="Variants">120-0.58/3</Category><Category descr="Drives">1-Phase Power Supply</Category><Category descr="Drives">No additional drive</Category><Option descr="RW Drive module 1 key"></Option><Option descr="ABB standard manipulator"><SubOption descr="IRB 120"><SubOption descr="120-0.58/3"></SubOption></SubOption></Option><Option descr="Drive System 09 120/140/1400/1600 Compact"><SubOption descr="1-Phase Power Supply"><SubOption descr="No additional drive"></SubOption></SubOption></Option></DriveModule></SystemProperties>
